examples/final/spi.sv
module spi(
    input  logic clk,       // System clock
    input  logic sclk,      // SPI clock
    input  logic cs_n,      // Chip Select (active low)
    input  logic mosi,      // Master Out, Slave In
    output logic [17:0] data_out, // 16-bit divider_value + 2-bit waveform_select
    output logic data_ready
);

    logic [4:0] bit_cnt;       // up to 18 bits (needs 5 bits counter)
    logic [17:0] shift_reg;
    logic sclk_prev;

    always_ff @(posedge clk) begin
        sclk_prev <= sclk;
        data_ready <= 1'b0;

        if (!cs_n) begin
            if (sclk_prev == 0 && sclk == 1) begin // rising edge on sclk
                shift_reg <= {shift_reg[16:0], mosi};
                bit_cnt <= bit_cnt + 1;

                if (bit_cnt == 5'd17) begin
                    data_out <= {shift_reg[16:0], mosi};
                    data_ready <= 1'b1;
                    bit_cnt <= 0;
                end
            end
        end else begin
            bit_cnt <= 0;
        end
    end

endmodule

examples/final/memory.sv
module memory #(
    parameter INIT_FILE = ""
)(
    input logic clk,
    input logic [8:0] read_address,
    output logic [9:0] read_data
);

    logic [8:0] quarter_cycle_memory [0:127]; // 9-bit amplitude (0-511)

    initial if (INIT_FILE) begin
        $readmemh(INIT_FILE, quarter_cycle_memory);
    end

    always_ff @(posedge clk) begin
        case (read_address[8:7])
            // Q1: 0-π/2 -> 512 to 1023 (512 + amplitude)
            2'b00: read_data <= 10'd512 + {1'b0, quarter_cycle_memory[read_address[6:0]]};
            
            // Q2: π/2-π -> 1023 to 512 (512 + mirrored amplitude)
            2'b01: read_data <= 10'd512 + {1'b0, quarter_cycle_memory[127 - read_address[6:0]]};
            
            // Q3: π-3π/2 -> 512 to 1 (512 - amplitude)
            2'b10: read_data <= 10'd512 - {1'b0, quarter_cycle_memory[read_address[6:0]]};
            
            // Q4: 3π/2-2π -> 1 to 512 (512 - mirrored amplitude)
            2'b11: read_data <= 10'd512 - {1'b0, quarter_cycle_memory[127 - read_address[6:0]]};
        endcase
    end

endmodule

examples/final/sine.sv
module top(
    input logic clk,
    input logic sclk,
    input logic cs_n,
    input logic mosi,
    output logic _9b, _6a, _4a, _2a, _0a, _5a, _3b, _49a, _45a, _48b
);

    logic [8:0] address = 9'd0;            // <-- FIX: Initialize to 0
    logic [9:0] sine_data;
    logic [9:0] output_data;
    
    logic [15:0] clk_divider = 16'd5;       // <-- FIX: Initialize to 5
    logic [15:0] divider_value = 16'd5;     // <-- FIX: Initialize to 5
    logic [1:0] waveform_select = 2'b00;    // <-- FIX: Initialize to 00

    logic [17:0] spi_data;
    logic spi_data_ready;

    // Precompute address slices
    logic address_bit8;
    logic [7:0] address_bits7_0;

    assign address_bit8 = address[8];
    assign address_bits7_0 = address[7:0];

    // Instantiate memory
    memory #(
        .INIT_FILE("sine.txt")
    ) u_memory (
        .clk(clk),
        .read_address(address),
        .read_data(sine_data)
    );

    // Instantiate SPI slave
    spi u_spi (
        .clk(clk),
        .sclk(sclk),
        .cs_n(cs_n),
        .mosi(mosi),
        .data_out(spi_data),
        .data_ready(spi_data_ready)
    );

    // Divider for stepping the address
    always_ff @(posedge clk) begin
        if (clk_divider == 0) begin
            clk_divider <= divider_value;
            if (address == 9'd511)  // optional: wrap-around at 511
                address <= 9'd0;
            else
                address <= address + 1;
        end else begin
            clk_divider <= clk_divider - 1;
        end
    end

    // Update divider value and waveform select from SPI
    always_ff @(posedge clk) begin
        if (spi_data_ready) begin
            divider_value <= spi_data[17:2];
            waveform_select <= spi_data[1:0];
        end
    end

    // Waveform generation
    logic [9:0] triangle_wave;
    logic [9:0] square_wave;

    always_comb begin
        if (address_bit8) begin
            triangle_wave = 10'd1023 - (address_bits7_0 << 2);
            square_wave = 10'd1023;
        end else begin
            triangle_wave = (address_bits7_0 << 2);
            square_wave = 10'd0;
        end

        case (waveform_select)
            2'b00: output_data = sine_data;
            2'b01: output_data = square_wave;
            2'b10: output_data = triangle_wave;
            default: output_data = 10'd0;
        endcase
    end

    // Output bit mapping
    assign _48b = output_data[9];
    assign _45a = output_data[8];
    assign _49a = output_data[7];
    assign _3b  = output_data[6];
    assign _5a  = output_data[5];
    assign _0a  = output_data[4];
    assign _2a  = output_data[3];
    assign _4a  = output_data[2];
    assign _6a  = output_data[1];
    assign _9b  = output_data[0];

endmodule

examples/final/sine_tb.sv
`timescale 10ns/10ns

module sine_tb;

    logic clk = 0;
    logic sclk = 0;
    logic cs_n = 1;
    logic mosi;

    logic _9b, _6a, _4a, _2a, _0a, _5a, _3b, _49a, _45a, _48b;

    // Instantiate top DUT
    top dut (
        .clk(clk),
        .sclk(sclk),
        .cs_n(cs_n),
        .mosi(mosi),
        ._9b(_9b),
        ._6a(_6a),
        ._4a(_4a),
        ._2a(_2a),
        ._0a(_0a),
        ._5a(_5a),
        ._3b(_3b),
        ._49a(_49a),
        ._45a(_45a),
        ._48b(_48b)
    );

    initial begin
        $dumpfile("sine.vcd");
        $dumpvars(0, sine_tb);

        // Wait a little before sending SPI
        #1000;

        // SPI send: Divider 500, waveform select 10 (triangle wave)
        spi_send(16'd500, 2'b10);

        #5000;

        // SPI send: Divider 1000, waveform select 00 (sine wave)
        spi_send(16'd1000, 2'b00);

        #5000;

        // SPI send: Divider 250, waveform select 01 (square wave)
        spi_send(16'd250, 2'b01);

        #30000;;

        $finish;
    end

    // Clock generation
    always #4 clk = ~clk;    // 125MHz
    always #10 sclk = ~sclk; // SPI clock slower

    task spi_send(input logic [15:0] divider, input logic [1:0] wform);
        logic [17:0] packet;
        integer i;
        begin
            packet = {divider, wform};
            cs_n = 0;
            for (i = 17; i >= 0; i = i - 1) begin
                mosi = packet[i];
                @(posedge sclk);
            end
            cs_n = 1;
            // small gap between transactions
            repeat (5) @(posedge clk);
        end
    endtask

endmodule

examples/final/sine.vcd
$date
	Mon Apr 28 12:18:52 2025
$end
$version
	Icarus Verilog
$end
$timescale
	10ns
$end
$scope module sine_tb $end
$var wire 1 ! _9b $end
$var wire 1 " _6a $end
$var wire 1 # _5a $end
$var wire 1 $ _4a $end
$var wire 1 % _49a $end
$var wire 1 & _48b $end
$var wire 1 ' _45a $end
$var wire 1 ( _3b $end
$var wire 1 ) _2a $end
$var wire 1 * _0a $end
$var reg 1 + clk $end
$var reg 1 , cs_n $end
$var reg 1 - mosi $end
$var reg 1 . sclk $end
$scope module dut $end
$var wire 1 + clk $end
$var wire 1 , cs_n $end
$var wire 1 - mosi $end
$var wire 1 . sclk $end
$var wire 1 / spi_data_ready $end
$var wire 18 0 spi_data [17:0] $end
$var wire 10 1 sine_data [9:0] $end
$var wire 8 2 address_bits7_0 [7:0] $end
$var wire 1 3 address_bit8 $end
$var wire 1 ! _9b $end
$var wire 1 " _6a $end
$var wire 1 # _5a $end
$var wire 1 $ _4a $end
$var wire 1 % _49a $end
$var wire 1 & _48b $end
$var wire 1 ' _45a $end
$var wire 1 ( _3b $end
$var wire 1 ) _2a $end
$var wire 1 * _0a $end
$var reg 9 4 address [8:0] $end
$var reg 16 5 clk_divider [15:0] $end
$var reg 16 6 divider_value [15:0] $end
$var reg 10 7 output_data [9:0] $end
$var reg 10 8 square_wave [9:0] $end
$var reg 10 9 triangle_wave [9:0] $end
$var reg 2 : waveform_select [1:0] $end
$scope module u_memory $end
$var wire 1 + clk $end
$var wire 9 ; read_address [8:0] $end
$var parameter 64 < INIT_FILE $end
$var reg 10 = read_data [9:0] $end
$upscope $end
$scope module u_spi $end
$var wire 1 + clk $end
$var wire 1 , cs_n $end
$var wire 1 - mosi $end
$var wire 1 . sclk $end
$var reg 5 > bit_cnt [4:0] $end
$var reg 18 ? data_out [17:0] $end
$var reg 1 / data_ready $end
$var reg 1 @ sclk_prev $end
$var reg 18 A shift_reg [17:0] $end
$upscope $end
$upscope $end
$scope task spi_send $end
$var reg 16 B divider [15:0] $end
$var reg 18 C packet [17:0] $end
$var reg 2 D wform [1:0] $end
$var integer 32 E i [31:0] $end
$upscope $end
$upscope $end
$enddefinitions $end
$comment Show the parameter values. $end
$dumpall
b111001101101001011011100110010100101110011101000111100001110100 <
$end
#0
$dumpvars
bx E
bx D
bx C
bx B
bx A
x@
bx ?
bx >
bx =
b0 ;
b0 :
b0 9
b0 8
bx 7
b101 6
b101 5
b0 4
03
b0 2
bx 1
bx 0
x/
0.
x-
1,
0+
x*
x)
x(
x'
x&
x%
x$
x#
x"
x!
$end
#4
1&
0'
0%
0(
0#
0*
0)
0$
0"
0!
b1000000000 7
b1000000000 1
b1000000000 =
b0 >
0/
0@
b100 5
1+
#8
0+
#10
1.
#12
b11 5
1@
1+
#16
0+
#20
0@
b10 5
1+
0.
#24
0+
#28
b1 5
1+
#30
1.
#32
0+
#36
1@
b0 5
1+
#40
0+
0.
#44
b100 9
b1 2
b1 4
b1 ;
b101 5
0@
1+
#48
0+
#50
1.
#52
1$
1"
b1000000110 7
b1000000110 1
b1000000110 =
1@
b100 5
1+
#56
0+
#60
b11 5
0@
1+
0.
#64
0+
#68
b10 5
1+
#70
1.
#72
0+
#76
b1 5
1@
1+
#80
0+
0.
#84
0@
b0 5
1+
#88
0+
#90
1.
#92
b1000 9
b10 2
b10 4
b10 ;
b101 5
1@
1+
#96
0+
#100
1)
0"
b1000001100 7
b1000001100 1
b1000001100 =
0@
b100 5
1+
0.
#104
0+
#108
b11 5
1+
#110
1.
#112
0+
#116
1@
b10 5
1+
#120
0+
0.
#124
b1 5
0@
1+
#128
0+
#130
1.
#132
1@
b0 5
1+
#136
0+
#140
b1100 9
b11 2
b11 4
b11 ;
b101 5
0@
1+
0.
#144
0+
#148
1*
0)
0$
1"
b1000010010 7
b1000010010 1
b1000010010 =
b100 5
1+
#150
1.
#152
0+
#156
b11 5
1@
1+
#160
0+
0.
#164
0@
b10 5
1+
#168
0+
#170
1.
#172
b1 5
1@
1+
#176
0+
#180
0@
b0 5
1+
0.
#184
0+
#188
b10000 9
b100 2
b100 4
b100 ;
b101 5
1+
#190
1.
#192
0+
#196
1)
0"
1!
b1000011001 7
b1000011001 1
b1000011001 =
1@
b100 5
1+
#200
0+
0.
#204
b11 5
0@
1+
#208
0+
#210
1.
#212
1@
b10 5
1+
#216
0+
#220
b1 5
0@
1+
0.
#224
0+
#228
b0 5
1+
#230
1.
#232
0+
#236
b10100 9
b101 2
b101 4
b101 ;
b101 5
1@
1+
#240
0+
0.
#244
1$
1"
b1000011111 7
b1000011111 1
b1000011111 =
0@
b100 5
1+
#248
0+
#250
1.
#252
b11 5
1@
1+
#256
0+
#260
0@
b10 5
1+
0.
#264
0+
#268
b1 5
1+
#270
1.
#272
0+
#276
1@
b0 5
1+
#280
0+
0.
#284
b11000 9
b110 2
b110 4
b110 ;
b101 5
0@
1+
#288
0+
#290
1.
#292
1#
0*
0)
0"
b1000100101 7
b1000100101 1
b1000100101 =
1@
b100 5
1+
#296
0+
#300
b11 5
0@
1+
0.
#304
0+
#308
b10 5
1+
#310
1.
#312
0+
#316
b1 5
1@
1+
#320
0+
0.
#324
0@
b0 5
1+
#328
0+
#330
1.
#332
b11100 9
b111 2
b111 4
b111 ;
b101 5
1@
1+
#336
0+
#340
1)
0$
1"
b1000101011 7
b1000101011 1
b1000101011 =
0@
b100 5
1+
0.
#344
0+
#348
b11 5
1+
#350
1.
#352
0+
#356
1@
b10 5
1+
#360
0+
0.
#364
b1 5
0@
1+
#368
0+
#370
1.
#372
1@
b0 5
1+
#376
0+
#380
b100000 9
b1000 2
b1000 4
b1000 ;
b101 5
0@
1+
0.
#384
0+
#388
1*
0)
0!
b1000110010 7
b1000110010 1
b1000110010 =
b100 5
1+
#390
1.
#392
0+
#396
b11 5
1@
1+
#400
0+
0.
#404
0@
b10 5
1+
#408
0+
#410
1.
#412
b1 5
1@
1+
#416
0+
#420
0@
b0 5
1+
0.
#424
0+
#428
b100100 9
b1001 2
b1001 4
b1001 ;
b101 5
1+
#430
1.
#432
0+
#436
1)
0"
b1000111000 7
b1000111000 1
b1000111000 =
1@
b100 5
1+
#440
0+
0.
#444
b11 5
0@
1+
#448
0+
#450
1.
#452
1@
b10 5
1+
#456
0+
#460
b1 5
0@
1+
0.
#464
0+
#468
b0 5
1+
#470
1.
#472
0+
#476
b101000 9
b1010 2
b1010 4
b1010 ;
b101 5
1@
1+
#480
0+
0.
#484
1$
1"
b1000111110 7
b1000111110 1
b1000111110 =
0@
b100 5
1+
#488
0+
#490
1.
#492
b11 5
1@
1+
#496
0+
#500
0@
b10 5
1+
0.
#504
0+
#508
b1 5
1+
#510
1.
#512
0+
#516
1@
b0 5
1+
#520
0+
0.
#524
b101100 9
b1011 2
b1011 4
b1011 ;
b101 5
0@
1+
#528
0+
#530
1.
#532
1(
0#
0*
0)
0"
b1001000100 7
b1001000100 1
b1001000100 =
1@
b100 5
1+
#536
0+
#540
b11 5
0@
1+
0.
#544
0+
#548
b10 5
1+
#550
1.
#552
0+
#556
b1 5
1@
1+
#560
0+
0.
#564
0@
b0 5
1+
#568
0+
#570
1.
#572
b110000 9
b1100 2
b1100 4
b1100 ;
b101 5
1@
1+
#576
0+
#580
1)
0$
1"
1!
b1001001011 7
b1001001011 1
b1001001011 =
0@
b100 5
1+
0.
#584
0+
#588
b11 5
1+
#590
1.
#592
0+
#596
1@
b10 5
1+
#600
0+
0.
#604
b1 5
0@
1+
#608
0+
#610
1.
#612
1@
b0 5
1+
#616
0+
#620
b110100 9
b1101 2
b1101 4
b1101 ;
b101 5
0@
1+
0.
#624
0+
#628
1*
0)
0"
b1001010001 7
b1001010001 1
b1001010001 =
b100 5
1+
#630
1.
#632
0+
#636
b11 5
1@
1+
#640
0+
0.
#644
0@
b10 5
1+
#648
0+
#650
1.
#652
b1 5
1@
1+
#656
0+
#660
0@
b0 5
1+
0.
#664
0+
#668
b111000 9
b1110 2
b1110 4
b1110 ;
b101 5
1+
#670
1.
#672
0+
#676
1$
1"
b1001010111 7
b1001010111 1
b1001010111 =
1@
b100 5
1+
#680
0+
0.
#684
b11 5
0@
1+
#688
0+
#690
1.
#692
1@
b10 5
1+
#696
0+
#700
b1 5
0@
1+
0.
#704
0+
#708
b0 5
1+
#710
1.
#712
0+
#716
b111100 9
b1111 2
b1111 4
b1111 ;
b101 5
1@
1+
#720
0+
0.
#724
1)
0"
b1001011101 7
b1001011101 1
b1001011101 =
0@
b100 5
1+
#728
0+
#730
1.
#732
b11 5
1@
1+
#736
0+
#740
0@
b10 5
1+
0.
#744
0+
#748
b1 5
1+
#750
1.
#752
0+
#756
1@
b0 5
1+
#760
0+
0.
#764
b1000000 9
b10000 2
b10000 4
b10000 ;
b101 5
0@
1+
#768
0+
#770
1.
#772
1#
0*
0)
0$
1"
b1001100011 7
b1001100011 1
b1001100011 =
1@
b100 5
1+
#776
0+
#780
b11 5
0@
1+
0.
#784
0+
#788
b10 5
1+
#790
1.
#792
0+
#796
b1 5
1@
1+
#800
0+
0.
#804
0@
b0 5
1+
#808
0+
#810
1.
#812
b1000100 9
b10001 2
b10001 4
b10001 ;
b101 5
1@
1+
#816
0+
#820
1)
0"
b1001101001 7
b1001101001 1
b1001101001 =
0@
b100 5
1+
0.
#824
0+
#828
b11 5
1+
#830
1.
#832
0+
#836
1@
b10 5
1+
#840
0+
0.
#844
b1 5
0@
1+
#848
0+
#850
1.
#852
1@
b0 5
1+
#856
0+
#860
b1001000 9
b10010 2
b10010 4
b10010 ;
b101 5
0@
1+
0.
#864
0+
#868
1*
0)
0!
b1001110000 7
b1001110000 1
b1001110000 =
b100 5
1+
#870
1.
#872
0+
#876
b11 5
1@
1+
#880
0+
0.
#884
0@
b10 5
1+
#888
0+
#890
1.
#892
b1 5
1@
1+
#896
0+
#900
0@
b0 5
1+
0.
#904
0+
#908
b1001100 9
b10011 2
b10011 4
b10011 ;
b101 5
1+
#910
1.
#912
0+
#916
1$
1"
b1001110110 7
b1001110110 1
b1001110110 =
1@
b100 5
1+
#920
0+
0.
#924
b11 5
0@
1+
#928
0+
#930
1.
#932
1@
b10 5
1+
#936
0+
#940
b1 5
0@
1+
0.
#944
0+
#948
b0 5
1+
#950
1.
#952
0+
#956
b1010000 9
b10100 2
b10100 4
b10100 ;
b101 5
1@
1+
#960
0+
0.
#964
1)
0"
b1001111100 7
b1001111100 1
b1001111100 =
0@
b100 5
1+
#968
0+
#970
1.
#972
b11 5
1@
1+
#976
0+
#980
0@
b10 5
1+
0.
#984
0+
#988
b1 5
1+
#990
1.
#992
0+
#996
1@
b0 5
1+
#1000
0+
0.
0-
b10001 E
0,
b11111010010 C
b10 D
b111110100 B
#1004
b1010100 9
b10101 2
b10101 4
b10101 ;
b101 5
0@
1+
#1008
0+
#1010
b10000 E
1.
#1012
1%
0(
0#
0*
0)
0$
1"
b1010000010 7
b1010000010 1
b1010000010 =
b1 >
bx0 A
1@
b100 5
1+
#1016
0+
#1020
b11 5
0@
1+
0.
#1024
0+
#1028
b10 5
1+
#1030
b1111 E
1.
#1032
0+
#1036
b1 5
b10 >
bx00 A
1@
1+
#1040
0+
0.
#1044
0@
b0 5
1+
#1048
0+
#1050
b1110 E
1.
#1052
b1011000 9
b10110 2
b10110 4
b10110 ;
b101 5
b11 >
bx000 A
1@
1+
#1056
0+
#1060
1)
0"
b1010001000 7
b1010001000 1
b1010001000 =
0@
b100 5
1+
0.
#1064
0+
#1068
b11 5
1+
#1070
b1101 E
1.
#1072
0+
#1076
b100 >
bx0000 A
1@
b10 5
1+
#1080
0+
0.
#1084
b1 5
0@
1+
#1088
0+
#1090
b1100 E
1.
#1092
b101 >
bx00000 A
1@
b0 5
1+
#1096
0+
#1100
b1011100 9
b10111 2
b10111 4
b10111 ;
b101 5
0@
1+
0.
#1104
0+
#1108
1$
1"
b1010001110 7
b1010001110 1
b1010001110 =
b100 5
1+
#1110
b1011 E
1.
#1112
0+
#1116
b11 5
b110 >
bx000000 A
1@
1+
#1120
0+
0.
#1124
0@
b10 5
1+
#1128
0+
#1130
1-
b1010 E
1.
#1132
b1 5
b111 >
bx0000001 A
1@
1+
#1136
0+
#1140
0@
b0 5
1+
0.
#1144
0+
#1148
b1100000 9
b11000 2
b11000 4
b11000 ;
b101 5
1+
#1150
b1001 E
1.
#1152
0+
#1156
1*
0)
0"
b1010010100 7
b1010010100 1
b1010010100 =
b1000 >
bx00000011 A
1@
b100 5
1+
#1160
0+
0.
#1164
b11 5
0@
1+
#1168
0+
#1170
b1000 E
1.
#1172
b1001 >
bx000000111 A
1@
b10 5
1+
#1176
0+
#1180
b1 5
0@
1+
0.
#1184
0+
#1188
b0 5
1+
#1190
b111 E
1.
#1192
0+
#1196
b1100100 9
b11001 2
b11001 4
b11001 ;
b101 5
b1010 >
bx0000001111 A
1@
1+
#1200
0+
0.
#1204
1)
0$
1"
b1010011010 7
b1010011010 1
b1010011010 =
0@
b100 5
1+
#1208
0+
#1210
b110 E
1.
#1212
b11 5
b1011 >
bx00000011111 A
1@
1+
#1216
0+
#1220
0@
b10 5
1+
0.
#1224
0+
#1228
b1 5
1+
#1230
0-
b101 E
1.
#1232
0+
#1236
b1100 >
bx000000111110 A
1@
b0 5
1+
#1240
0+
0.
#1244
b1101000 9
b11010 2
b11010 4
b11010 ;
b101 5
0@
1+
#1248
0+
#1250
1-
b100 E
1.
#1252
1#
0*
0)
0"
b1010100000 7
b1010100000 1
b1010100000 =
b1101 >
bx0000001111101 A
1@
b100 5
1+
#1256
0+
#1260
b11 5
0@
1+
0.
#1264
0+
#1268
b10 5
1+
#1270
0-
b11 E
1.
#1272
0+
#1276
b1 5
b1110 >
bx00000011111010 A
1@
1+
#1280
0+
0.
#1284
0@
b0 5
1+
#1288
0+
#1290
b10 E
1.
#1292
b1101100 9
b11011 2
b11011 4
b11011 ;
b101 5
b1111 >
bx000000111110100 A
1@
1+
#1296
0+
#1300
1$
1"
b1010100110 7
b1010100110 1
b1010100110 =
0@
b100 5
1+
0.
#1304
0+
#1308
b11 5
1+
#1310
1-
b1 E
1.
#1312
0+
#1316
b10000 >
bx0000001111101001 A
1@
b10 5
1+
#1320
0+
0.
#1324
b1 5
0@
1+
#1328
0+
#1330
0-
b0 E
1.
#1332
b10001 >
bx00000011111010010 A
1@
b0 5
1+
#1336
0+
#1340
b1110000 9
b11100 2
b11100 4
b11100 ;
b101 5
0@
1+
0.
#1344
0+
#1348
1)
0"
b1010101100 7
b1010101100 1
b1010101100 =
b100 5
1+
#1350
1,
b11111111111111111111111111111111 E
1.
#1352
0+
#1356
b11 5
b0 >
1@
1+
#1360
0+
0.
#1364
0@
b10 5
1+
#1368
0+
#1370
1.
#1372
b1 5
1@
1+
#1376
0+
#1380
0@
b0 5
1+
0.
#1384
0+
#1388
b1110100 9
b11101 2
b11101 4
b11101 ;
b101 5
1+
#1390
1.
#1392
0+
#1396
1*
0)
0$
1"
b1010110010 7
b1010110010 1
b1010110010 =
1@
b100 5
1+
#1400
0+
0.
#1404
b11 5
0@
1+
#1408
0+
#1410
1.
#1412
1@
b10 5
1+
#1416
0+
#1420
b1 5
0@
1+
0.
#1424
0+
#1428
b0 5
1+
#1430
1.
#1432
0+
#1436
b1111000 9
b11110 2
b11110 4
b11110 ;
b101 5
1@
1+
#1440
0+
0.
#1444
1)
0"
b1010111000 7
b1010111000 1
b1010111000 =
0@
b100 5
1+
#1448
0+
#1450
1.
#1452
b11 5
1@
1+
#1456
0+
#1460
0@
b10 5
1+
0.
#1464
0+
#1468
b1 5
1+
#1470
1.
#1472
0+
#1476
1@
b0 5
1+
#1480
0+
0.
#1484
b1111100 9
b11111 2
b11111 4
b11111 ;
b101 5
0@
1+
#1488
0+
#1490
1.
#1492
1$
1!
b1010111101 7
b1010111101 1
b1010111101 =
1@
b100 5
1+
#1496
0+
#1500
b11 5
0@
1+
0.
#1504
0+
#1508
b10 5
1+
#1510
1.
#1512
0+
#1516
b1 5
1@
1+
#1520
0+
0.
#1524
0@
b0 5
1+
#1528
0+
#1530
1.
#1532
b10000000 9
b100000 2
b100000 4
b100000 ;
b101 5
1@
1+
#1536
0+
#1540
1(
0#
0*
0)
0$
1"
b1011000011 7
b1011000011 1
b1011000011 =
0@
b100 5
1+
0.
#1544
0+
#1548
b11 5
1+
#1550
1.
#1552
0+
#1556
1@
b10 5
1+
#1560
0+
0.
#1564
b1 5
0@
1+
#1568
0+
#1570
1.
#1572
1@
b0 5
1+
#1576
0+
#1580
b10000100 9
b100001 2
b100001 4
b100001 ;
b101 5
0@
1+
0.
#1584
0+
#1588
1)
0"
b1011001001 7
b1011001001 1
b1011001001 =
b100 5
1+
#1590
1.
#1592
0+
#1596
b11 5
1@
1+
#1600
0+
0.
#1604
0@
b10 5
1+
#1608
0+
#1610
1.
#1612
b1 5
1@
1+
#1616
0+
#1620
0@
b0 5
1+
0.
#1624
0+
#1628
b10001000 9
b100010 2
b100010 4
b100010 ;
b101 5
1+
#1630
1.
#1632
0+
#1636
1$
1"
b1011001111 7
b1011001111 1
b1011001111 =
1@
b100 5
1+
#1640
0+
0.
#1644
b11 5
0@
1+
#1648
0+
#1650
1.
#1652
1@
b10 5
1+
#1656
0+
#1660
b1 5
0@
1+
0.
#1664
0+
#1668
b0 5
1+
#1670
1.
#1672
0+
#1676
b10001100 9
b100011 2
b100011 4
b100011 ;
b101 5
1@
1+
#1680
0+
0.
#1684
1*
0)
0"
b1011010101 7
b1011010101 1
b1011010101 =
0@
b100 5
1+
#1688
0+
#1690
1.
#1692
b11 5
1@
1+
#1696
0+
#1700
0@
b10 5
1+
0.
#1704
0+
#1708
b1 5
1+
#1710
1.
#1712
0+
#1716
1@
b0 5
1+
#1720
0+
0.
#1724
b10010000 9
b100100 2
b100100 4
b100100 ;
b101 5
0@
1+
#1728
0+
#1730
1.
#1732
1)
0$
1"
0!
b1011011010 7
b1011011010 1
b1011011010 =
1@
b100 5
1+
#1736
0+
#1740
b11 5
0@
1+
0.
#1744
0+
#1748
b10 5
1+
#1750
1.
#1752
0+
#1756
b1 5
1@
1+
#1760
0+
0.
#1764
0@
b0 5
1+
#1768
0+
#1770
1.
#1772
b10010100 9
b100101 2
b100101 4
b100101 ;
b101 5
1@
1+
#1776
0+
#1780
1#
0*
0)
0"
b1011100000 7
b1011100000 1
b1011100000 =
0@
b100 5
1+
0.
#1784
0+
#1788
b11 5
1+
#1790
1.
#1792
0+
#1796
1@
b10 5
1+
#1800
0+
0.
#1804
b1 5
0@
1+
#1808
0+
#1810
1.
#1812
1@
b0 5
1+
#1816
0+
#1820
b10011000 9
b100110 2
b100110 4
b100110 ;
b101 5
0@
1+
0.
#1824
0+
#1828
1$
1!
b1011100101 7
b1011100101 1
b1011100101 =
b100 5
1+
#1830
1.
#1832
0+
#1836
b11 5
1@
1+
#1840
0+
0.
#1844
0@
b10 5
1+
#1848
0+
#1850
1.
#1852
b1 5
1@
1+
#1856
0+
#1860
0@
b0 5
1+
0.
#1864
0+
#1868
b10011100 9
b100111 2
b100111 4
b100111 ;
b101 5
1+
#1870
1.
#1872
0+
#1876
1)
0$
1"
b1011101011 7
b1011101011 1
b1011101011 =
1@
b100 5
1+
#1880
0+
0.
#1884
b11 5
0@
1+
#1888
0+
#1890
1.
#1892
1@
b10 5
1+
#1896
0+
#1900
b1 5
0@
1+
0.
#1904
0+
#1908
b0 5
1+
#1910
1.
#1912
0+
#1916
b10100000 9
b101000 2
b101000 4
b101000 ;
b101 5
1@
1+
#1920
0+
0.
#1924
1*
0)
0"
b1011110001 7
b1011110001 1
b1011110001 =
0@
b100 5
1+
#1928
0+
#1930
1.
#1932
b11 5
1@
1+
#1936
0+
#1940
0@
b10 5
1+
0.
#1944
0+
#1948
b1 5
1+
#1950
1.
#1952
0+
#1956
1@
b0 5
1+
#1960
0+
0.
#1964
b10100100 9
b101001 2
b101001 4
b101001 ;
b101 5
0@
1+
#1968
0+
#1970
1.
#1972
1$
1"
0!
b1011110110 7
b1011110110 1
b1011110110 =
1@
b100 5
1+
#1976
0+
#1980
b11 5
0@
1+
0.
#1984
0+
#1988
b10 5
1+
#1990
1.
#1992
0+
#1996
b1 5
1@
1+
#2000
0+
0.
#2004
0@
b0 5
1+
#2008
0+
#2010
1.
#2012
b10101000 9
b101010 2
b101010 4
b101010 ;
b101 5
1@
1+
#2016
0+
#2020
1)
0"
b1011111100 7
b1011111100 1
b1011111100 =
0@
b100 5
1+
0.
#2024
0+
#2028
b11 5
1+
#2030
1.
#2032
0+
#2036
1@
b10 5
1+
#2040
0+
0.
#2044
b1 5
0@
1+
#2048
0+
#2050
1.
#2052
1@
b0 5
1+
#2056
0+
#2060
b10101100 9
b101011 2
b101011 4
b101011 ;
b101 5
0@
1+
0.
#2064
0+
#2068
1'
0%
0(
0#
0*
0)
0$
1!
b1100000001 7
b1100000001 1
b1100000001 =
b100 5
1+
#2070
1.
#2072
0+
#2076
b11 5
1@
1+
#2080
0+
0.
#2084
0@
b10 5
1+
#2088
0+
#2090
1.
#2092
b1 5
1@
1+
#2096
0+
#2100
0@
b0 5
1+
0.
#2104
0+
#2108
b10110000 9
b101100 2
b101100 4
b101100 ;
b101 5
1+
#2110
1.
#2112
0+
#2116
1$
1"
0!
b1100000110 7
b1100000110 1
b1100000110 =
1@
b100 5
1+
#2120
0+
0.
#2124
b11 5
0@
1+
#2128
0+
#2130
1.
#2132
1@
b10 5
1+
#2136
0+
#2140
b1 5
0@
1+
0.
#2144
0+
#2148
b0 5
1+
#2150
1.
#2152
0+
#2156
b10110100 9
b101101 2
b101101 4
b101101 ;
b101 5
1@
1+
#2160
0+
0.
#2164
1)
0"
b1100001100 7
b1100001100 1
b1100001100 =
0@
b100 5
1+
#2168
0+
#2170
1.
#2172
b11 5
1@
1+
#2176
0+
#2180
0@
b10 5
1+
0.
#2184
0+
#2188
b1 5
1+
#2190
1.
#2192
0+
#2196
1@
b0 5
1+
#2200
0+
0.
#2204
b10111000 9
b101110 2
b101110 4
b101110 ;
b101 5
0@
1+
#2208
0+
#2210
1.
#2212
1*
0)
0$
1!
b1100010001 7
b1100010001 1
b1100010001 =
1@
b100 5
1+
#2216
0+
#2220
b11 5
0@
1+
0.
#2224
0+
#2228
b10 5
1+
#2230
1.
#2232
0+
#2236
b1 5
1@
1+
#2240
0+
0.
#2244
0@
b0 5
1+
#2248
0+
#2250
1.
#2252
b10111100 9
b101111 2
b101111 4
b101111 ;
b101 5
1@
1+
#2256
0+
#2260
1$
1"
0!
b1100010110 7
b1100010110 1
b1100010110 =
0@
b100 5
1+
0.
#2264
0+
#2268
b11 5
1+
#2270
1.
#2272
0+
#2276
1@
b10 5
1+
#2280
0+
0.
#2284
b1 5
0@
1+
#2288
0+
#2290
1.
#2292
1@
b0 5
1+
#2296
0+
#2300
b11000000 9
b110000 2
b110000 4
b110000 ;
b101 5
0@
1+
0.
#2304
0+
#2308
1)
0"
b1100011100 7
b1100011100 1
b1100011100 =
b100 5
1+
#2310
1.
#2312
0+
#2316
b11 5
1@
1+
#2320
0+
0.
#2324
0@
b10 5
1+
#2328
0+
#2330
1.
#2332
b1 5
1@
1+
#2336
0+
#2340
0@
b0 5
1+
0.
#2344
0+
#2348
b11000100 9
b110001 2
b110001 4
b110001 ;
b101 5
1+
#2350
1.
#2352
0+
#2356
1#
0*
0)
0$
1!
b1100100001 7
b1100100001 1
b1100100001 =
1@
b100 5
1+
#2360
0+
0.
#2364
b11 5
0@
1+
#2368
0+
#2370
1.
#2372
1@
b10 5
1+
#2376
0+
#2380
b1 5
0@
1+
0.
#2384
0+
#2388
b0 5
1+
#2390
1.
#2392
0+
#2396
b11001000 9
b110010 2
b110010 4
b110010 ;
b101 5
1@
1+
#2400
0+
0.
#2404
1$
1"
0!
b1100100110 7
b1100100110 1
b1100100110 =
0@
b100 5
1+
#2408
0+
#2410
1.
#2412
b11 5
1@
1+
#2416
0+
#2420
0@
b10 5
1+
0.
#2424
0+
#2428
b1 5
1+
#2430
1.
#2432
0+
