examples/miniproj4/alu.sv
module alu (
    input  logic [31:0] src1,
    input  logic [31:0] src2,
    input  logic [3:0]  aluc,
    output logic [31:0] out,
    output logic        zero,
    output logic        cout,
    output logic        overflow,
    output logic        sign
);

    logic [32:0] tmp;
    logic [4:0]  shamt;

    assign shamt = src2[4:0];  // ONLY allowed here as continuous assign

    always @(*) begin
        out = 32'd0;
        tmp = 33'd0;
        cout = 1'b0;
        overflow = 1'b0;

        case (aluc)
            4'b0000: begin // ADD
                tmp = {1'b0, src1} + {1'b0, src2};
                out = tmp[31:0];
                cout = tmp[32];
                overflow = (src1[31] == src2[31]) && (out[31] != src1[31]);
            end

            4'b0001: begin // SUB
                tmp = {1'b0, src1} - {1'b0, src2};
                out = tmp[31:0];
                cout = tmp[32];
                overflow = (src1[31] != src2[31]) && (out[31] != src1[31]);
            end

            4'b0010: out = src1 & src2;  // AND
            4'b0011: out = src1 | src2;  // OR
            4'b0100: out = src1 ^ src2;  // XOR
            4'b0101: out = $signed(src1) < $signed(src2) ? 32'd1 : 32'd0;  // SLT
            4'b0110: out = (src1 < src2) ? 32'd1 : 32'd0;  // SLTU
            4'b0111: out = src1 << shamt; // SLL
            4'b1000: out = src1 >> shamt; // SRL
            4'b1001: out = $signed(src1) >>> shamt; // SRA
            default: out = 32'd0;
        endcase

        zero = (out == 32'd0);
        sign = out[31];
    end

endmodule

examples/miniproj4/alu_tb.sv
`timescale 1ns/1ns
`include "alu.sv"

module alu_tb;

  logic [31:0] src1, src2;
  logic [3:0]  aluc;
  logic [31:0] out;
  logic        zero, cout, overflow, sign;

  alu dut (
    .src1(src1),
    .src2(src2),
    .aluc(aluc),
    .out(out),
    .zero(zero),
    .cout(cout),
    .overflow(overflow),
    .sign(sign)
  );

  // Helper task for checking output
  task automatic check(string name, logic [31:0] expected);
    if (out !== expected) begin
      $display("FAIL: %s | src1=%0d, src2=%0d => out=%h (expected %h)", name, src1, src2, out, expected);
      $fatal;
    end else begin
      $display("PASS: %s | out=%h", name, out);
    end
  endtask

  initial begin
    $display("\n===== ALU Test Start =====");
    $dumpfile("alu_tb.vcd");
    $dumpvars(0, alu_tb);

    // ADD: 15 + 10 = 25
    src1 = 32'd15; src2 = 32'd10; aluc = 4'b0000; #1;
    check("ADD", 32'd25);

    // SUB: 20 - 10 = 10
    src1 = 32'd20; src2 = 32'd10; aluc = 4'b0001; #1;
    check("SUB", 32'd10);

    // AND
    src1 = 32'hFF00FF00; src2 = 32'h0F0F0F0F; aluc = 4'b0010; #1;
    check("AND", 32'h0F000F00);

    // OR
    src1 = 32'hFF00FF00; src2 = 32'h0F0F0F0F; aluc = 4'b0011; #1;
    check("OR", 32'hFF0FFF0F);

    // XOR
    src1 = 32'hFFFF0000; src2 = 32'h00FFFF00; aluc = 4'b0100; #1;
    check("XOR", 32'hFF00FF00);

    // SLT (signed): -5 < 2 => 1
    src1 = -5; src2 = 2; aluc = 4'b0101; #1;
    check("SLT", 32'd1);

    // SLTU (unsigned): 5 < 2 => 0
    src1 = 5; src2 = 2; aluc = 4'b0110; #1;
    check("SLTU", 32'd0);

    // SLL (shift left logical): 1 << 3 = 8
    src1 = 32'd1; src2 = 32'd3; aluc = 4'b0111; #1;
    check("SLL", 32'd8);

    // SRL (shift right logical): 0x80000000 >> 2 = 0x20000000
    src1 = 32'h80000000; src2 = 32'd2; aluc = 4'b1000; #1;
    check("SRL", 32'h20000000);

    // SRA (arithmetic shift): -4 >>> 1 = -2
    src1 = -4; src2 = 32'd1; aluc = 4'b1001; #1;
    check("SRA", -2);

    $display("🎉 All ALU tests passed!");
    $finish;
  end

endmodule

examples/miniproj4/alu_tb.vcd
$date
	Thu Apr 24 16:50:48 2025
$end
$version
	Icarus Verilog
$end
$timescale
	1ns
$end
$scope module alu_tb $end
$var wire 1 ! zero $end
$var wire 1 " sign $end
$var wire 1 # overflow $end
$var wire 32 $ out [31:0] $end
$var wire 1 % cout $end
$var reg 4 & aluc [3:0] $end
$var reg 32 ' src1 [31:0] $end
$var reg 32 ( src2 [31:0] $end
$scope module dut $end
$var wire 4 ) aluc [3:0] $end
$var wire 32 * src1 [31:0] $end
$var wire 32 + src2 [31:0] $end
$var wire 5 , shamt [4:0] $end
$var reg 1 % cout $end
$var reg 32 - out [31:0] $end
$var reg 1 # overflow $end
$var reg 1 " sign $end
$var reg 33 . tmp [32:0] $end
$var reg 1 ! zero $end
$upscope $end
$scope task check $end
$upscope $end
$upscope $end
$enddefinitions $end
$comment Show the parameter values. $end
$dumpall
$end
#0
$dumpvars
b11001 .
b11001 -
b1010 ,
b1010 +
b1111 *
b0 )
b1010 (
b1111 '
b0 &
0%
b11001 $
0#
0"
0!
$end
#1
b1010 .
b1010 $
b1010 -
b1 &
b1 )
b10100 '
b10100 *
#2
b1111 ,
b0 .
b1111000000000000111100000000 $
b1111000000000000111100000000 -
b10 &
b10 )
b1111000011110000111100001111 (
b1111000011110000111100001111 +
b11111111000000001111111100000000 '
b11111111000000001111111100000000 *
#3
1"
b11111111000011111111111100001111 $
b11111111000011111111111100001111 -
b11 &
b11 )
#4
b0 ,
1"
b11111111000000001111111100000000 $
b11111111000000001111111100000000 -
b100 &
b100 )
b111111111111111100000000 (
b111111111111111100000000 +
b11111111111111110000000000000000 '
b11111111111111110000000000000000 *
#5
b10 ,
0"
b1 $
b1 -
b101 &
b101 )
b10 (
b10 +
b11111111111111111111111111111011 '
b11111111111111111111111111111011 *
#6
1!
b0 $
b0 -
b110 &
b110 )
b101 '
b101 *
#7
b11 ,
b1000 $
b1000 -
0!
b111 &
b111 )
b11 (
b11 +
b1 '
b1 *
#8
b10 ,
b100000000000000000000000000000 $
b100000000000000000000000000000 -
b1000 &
b1000 )
b10 (
b10 +
b10000000000000000000000000000000 '
b10000000000000000000000000000000 *
#9
b1 ,
1"
b11111111111111111111111111111110 $
b11111111111111111111111111111110 -
b1001 &
b1001 )
b1 (
b1 +
b11111111111111111111111111111100 '
b11111111111111111111111111111100 *
