examples/miniproj4/flopr.sv
// for initial datapath file

module flopr #(parameter WIDTH = 8) (
    input  logic             clk,    // Clock input
    input  logic             reset,  // Asynchronous reset (active-high)
    input  logic [WIDTH-1:0] d,      // Data input
    output logic [WIDTH-1:0] q       // Data output
);

    always_ff @(posedge clk, posedge reset) begin
        if (reset)  q <= '0;    // Clear all bits on reset
        else        q <= d;     // Update on every clock edge
    end

endmodule

examples/miniproj4/flopenr.sv
module flopenr #(parameter WIDTH = 32) (
    input  logic              clk,
    input  logic              reset,    // Synchronous reset
    input  logic             en,
    input  logic [WIDTH-1:0]  d,
    output logic [WIDTH-1:0]  q
);
    always_ff @(posedge clk) begin
        if (reset)
            q <= '0;
        else
            q <= d;
    end
endmodule

examples/miniproj4/mux2.sv
module mux2 #(parameter WIDTH = 32) (
    input  logic [WIDTH-1:0] a, b,
    input  logic             sel,
    output logic [WIDTH-1:0] out
);
    assign out = sel ? b : a;
endmodule

examples/miniproj4/mux4.sv
module mux4 #(parameter WIDTH = 32) (
    input  logic [WIDTH-1:0] in0, in1, in2, in3,
    input  logic [1:0] sel,
    output logic [WIDTH-1:0] out
);
    always_comb begin
        case (sel)
            2'b00: out = in0;
            2'b01: out = in1;
            2'b10: out = in2;
            2'b11: out = in3;
        endcase
    end
endmodule

examples/miniproj4/alu.sv
module alu (
    input  logic [31:0] src1,
    input  logic [31:0] src2,
    input  logic [3:0]  aluc,
    output logic [31:0] out,
    output logic        zero,
    output logic        cout,
    output logic        overflow,
    output logic        sign
);

    logic [32:0] tmp;
    logic [4:0]  shamt;

    assign shamt = src2[4:0];  // ONLY allowed here as continuous assign

    always @(*) begin
        out = 32'd0;
        tmp = 33'd0;
        cout = 1'b0;
        overflow = 1'b0;

        case (aluc)
            4'b0000: begin // ADD
                tmp = {1'b0, src1} + {1'b0, src2};
                out = tmp[31:0];
                cout = tmp[32];
                overflow = (src1[31] == src2[31]) && (out[31] != src1[31]);
            end

            4'b0001: begin // SUB
                tmp = {1'b0, src1} - {1'b0, src2};
                out = tmp[31:0];
                cout = tmp[32];
                overflow = (src1[31] != src2[31]) && (out[31] != src1[31]);
            end

            4'b0010: out = src1 & src2;  // AND
            4'b0011: out = src1 | src2;  // OR
            4'b0100: out = src1 ^ src2;  // XOR
            4'b0101: out = $signed(src1) < $signed(src2) ? 32'd1 : 32'd0;  // SLT
            4'b0110: out = (src1 < src2) ? 32'd1 : 32'd0;  // SLTU
            4'b0111: out = src1 << shamt; // SLL
            4'b1000: out = src1 >> shamt; // SRL
            4'b1001: out = $signed(src1) >>> shamt; // SRA
            default: out = 32'd0;
        endcase

        zero = (out == 32'd0);
        sign = out[31];
    end

endmodule

examples/miniproj4/mux3.sv
module mux3 #(parameter WIDTH = 32) (
    input  logic [WIDTH-1:0] in0, in1, in2,
    input  logic [1:0] sel,
    output logic [WIDTH-1:0] out
);
    always_comb begin
        case (sel)
            2'b00: out = in0;
            2'b01: out = in1;
            2'b10: out = in2;
            default: out = '0;
        endcase
    end
endmodule

examples/miniproj4/imm_gen.sv
module extend (
    input  logic [31:7] instr,
    input  logic [2:0]  ImmSrc,
    output logic [31:0] imm_out
);

    logic [31:0] imm_i, imm_s, imm_b, imm_u, imm_j;

    // Pre-decode all possible immediates
    assign imm_i = {{20{instr[31]}}, instr[31:20]};                                                  // I-type
    assign imm_s = {{20{instr[31]}}, instr[31:25], instr[11:7]};                                     // S-type
    assign imm_b = {{19{instr[31]}}, instr[31], instr[7], instr[30:25], instr[11:8], 1'b0};          // B-type
    assign imm_u = {instr[31:12], 12'b0};                                                            // U-type
    assign imm_j = {{11{instr[31]}}, instr[31], instr[19:12], instr[20], instr[30:21], 1'b0};        // J-type

    // Use case statement to select which immediate
    always_comb begin
        case (ImmSrc)
            3'b000: imm_out = imm_i;
            3'b001: imm_out = imm_s;
            3'b010: imm_out = imm_b;
            3'b011: imm_out = imm_u;
            3'b100: imm_out = imm_j;
            default: imm_out = 32'd0;
        endcase
    end

endmodule

examples/miniproj4/reg.sv
module register_file (
    input  logic        clk,
    input  logic        we,
    input  logic [4:0]  rs1,
    input  logic [4:0]  rs2,
    input  logic [4:0]  rd,
    input  logic [31:0] wd,
    output logic [31:0] rd1,
    output logic [31:0] rd2
);

    logic [31:0] rf[31:0];
    logic [31:0] rd1_reg, rd2_reg;

    // Synchronous write
    always_ff @(posedge clk) begin
        if (we && rd != 5'd0)
            rf[rd] <= wd;
        // Synchronous read
        rd1_reg <= (rs1 != 5'd0) ? rf[rs1] : 32'd0;
        rd2_reg <= (rs2 != 5'd0) ? rf[rs2] : 32'd0;
    end

    assign rd1 = rd1_reg;
    assign rd2 = rd2_reg;

endmodule

examples/miniproj4/dataPath.sv
`include "flopenr.sv"
`include "flopr.sv"
`include "mux2.sv"
`include "mux3.sv"
`include "mux4.sv"
`include "alu.sv"
`include "imm_gen.sv"
`include "reg.sv"

module dataPath (
    input  logic        clk, reset,
    input  logic [3:0]  ALUControl,
    input  logic [1:0]  ResultSrc,
    input  logic        IRWrite,
    input  logic        RegWrite,
    input  logic [1:0]  ALUSrcA, ALUSrcB,
    input  logic        AdrSrc,
    input  logic        PCWrite,
    input  logic [2:0]  ImmSrc,
    input  logic [31:0] ReadData,
    input  logic        memwrite,
    output logic        Zero, cout, overflow, sign,
    output logic [31:0] Adr,
    output logic [31:0] WriteData,
    output logic [31:0] instr
);

    // Internal wires/regs
    logic [31:0] Result, ALUOut, ALUResult;
    logic [31:0] RD1, RD2, A, SrcA, SrcB, Data;
    logic [31:0] ImmExt;
    logic [31:0] PC, OldPC;
    logic [31:0] aligned_address;
    logic [2:0]  funct3; // <-- Used instead of instr[14:12]

    // Extract instr[14:12] safely outside procedural block
    assign funct3 = instr[14:12];

    // PC register
    flopenr #(32) pcFlop(clk, reset, PCWrite, Result, PC);

    // Register file
    register_file rf (
        .clk(clk),
        .we(RegWrite),
        .rs1(instr[19:15]),
        .rs2(instr[24:20]),
        .rd(instr[11:7]),
        .wd(Result),
        .rd1(RD1),
        .rd2(RD2)
    );

    // Immediate extension
    extend ext (
        .instr(instr[31:7]),
        .ImmSrc(ImmSrc),
        .imm_out(ImmExt)
    );

    // Operand registers
    flopr #(32) AReg(clk, reset, RD1, A);
    flopr #(32) BReg(clk, reset, RD2, WriteData);

    // ALU operand selection
    mux3 #(32) srcAmux (
        .in0(PC),
        .in1(OldPC),
        .in2(A),
        .sel(ALUSrcA),
        .out(SrcA)
    );

    mux3 #(32) srcBmux (
        .in0(WriteData),
        .in1(ImmExt),
        .in2(32'd4),
        .sel(ALUSrcB),
        .out(SrcB)
    );

    // ALU
    alu alu (
        .src1(SrcA),
        .src2(SrcB),
        .aluc(ALUControl),
        .out(ALUResult),
        .zero(Zero),
        .cout(cout),
        .overflow(overflow),
        .sign(sign)
    );

    // ALU output register
    flopr #(32) aluReg(clk, reset, ALUResult, ALUOut);

    // Result selection
    mux4 #(32) resultMux (
        .in0(ALUOut),
        .in1(Data),
        .in2(ImmExt),
        .in3(32'h0),
        .sel(ResultSrc),
        .out(Result)
    );

    // Address mux
    mux2 #(32) adrMux (
        .a(PC),
        .b(aligned_address),
        .sel(AdrSrc),
        .out(Adr)
    );

    // IR and PC history registers
    flopenr #(32) oldPcReg(clk, reset, IRWrite, PC, OldPC);
    flopenr #(32) instrReg(clk, reset, IRWrite, ReadData, instr);
    flopr   #(32) dataReg(clk, reset, ReadData, Data);

    // Aligned address logic — now uses funct3 instead of instr[14:12]
    always @* begin
        case (funct3)
            3'b000: aligned_address = ALUOut;                        // SB
            3'b001: aligned_address = {ALUOut[31:1], 1'b0};          // SH
            3'b010: aligned_address = {ALUOut[31:2], 2'b00};         // SW
            default: aligned_address = ALUOut;
        endcase
    end

endmodule

examples/miniproj4/datapath_tb.sv
`timescale 1ns/1ns
`include "dataPath.sv"

module dataPath_tb;

  logic clk, reset;

  // Control signals
  logic [3:0]  ALUControl;
  logic [1:0]  ResultSrc;
  logic        IRWrite, RegWrite;
  logic [1:0]  ALUSrcA, ALUSrcB;
  logic        AdrSrc, PCWrite;
  logic [2:0]  ImmSrc;

  // Inputs
  logic [31:0] ReadData;

  // Outputs
  logic        Zero, cout, overflow, sign;
  logic [31:0] Adr, WriteData, instr;

  // DUT
  dataPath dut (
    .clk(clk),
    .reset(reset),
    .ALUControl(ALUControl),
    .ResultSrc(ResultSrc),
    .IRWrite(IRWrite),
    .RegWrite(RegWrite),
    .ALUSrcA(ALUSrcA),
    .ALUSrcB(ALUSrcB),
    .AdrSrc(AdrSrc),
    .PCWrite(PCWrite),
    .ImmSrc(ImmSrc),
    .ReadData(ReadData),
    .memwrite(1'b0),
    .Zero(Zero),
    .cout(cout),
    .overflow(overflow),
    .sign(sign),
    .Adr(Adr),
    .WriteData(WriteData),
    .instr(instr)
  );

  // Clock generation
  always #5 clk = ~clk;

  initial begin
    $dumpfile("dataPath_tb.vcd");
    $dumpvars(0, dataPath_tb);

    clk = 0;
    reset = 0;

    // Synchronous reset
    @(negedge clk); reset = 1;
    @(negedge clk); reset = 0;

    $display("\n========== WRITE DATA FUNCTIONAL TEST ==========");

    // -------------------------------------
    // Step 1: Write 0x14E into register x5 using ADDI
    // ADDI x5, x0, 0x14E (334)
    // Encoding: imm[11:0]=0x14E, rs1=0, funct3=000, rd=5, opcode=0010011
    ReadData = 32'h014E0005 | 32'h00100113; // Correct ADDI encoding
    IRWrite  = 1;
    @(negedge clk); 
    IRWrite = 0;

    // Configure control signals for ADDI
    RegWrite   = 1;
    ResultSrc  = 2'b00;  // Result = ALUOut
    ImmSrc     = 3'b000; // I-type
    ALUSrcA    = 2'b10;  // Register A (rs1 = x0)
    ALUSrcB    = 2'b01;  // ImmExt
    ALUControl = 4'b0000; // ADD

    // Wait for write to complete
    @(negedge clk);
    RegWrite = 0;

    // -------------------------------------
    // Step 2: Read x5 via ADD instruction
    // ADD x0, x0, x5 (rs2 = 5)
    // Encoding: funct7=0000000, rs2=5, rs1=0, funct3=000, rd=0, opcode=0110011
    ReadData = 32'h00500033; // Correct ADD encoding
    IRWrite  = 1;
    @(negedge clk);
    IRWrite = 0;

    // Configure control signals for ADD
    ALUSrcA    = 2'b10;  // Register A
    ALUSrcB    = 2'b00;  // Register B
    ALUControl = 4'b0000; // ADD

    // Allow time for BReg to update
    @(negedge clk);

    // -------------------------------------
    // Step 3: Verify WriteData == 0x14E
    $display("WriteData observed: %h", WriteData);
    if (WriteData !== 32'h0000014E) begin
      $fatal(1, "ERROR: Expected 0x0000014E, got %h", WriteData);
    end else begin
      $display("SUCCESS: WriteData correct");
    end

    $display("Test completed.");
    $finish;
  end

endmodule

examples/miniproj4/dataPath_tb.vcd
$date
	Thu Apr 24 17:17:42 2025
$end
$version
	Icarus Verilog
$end
$timescale
	1ns
$end
$scope module dataPath_tb $end
$var wire 1 ! sign $end
$var wire 1 " overflow $end
$var wire 32 # instr [31:0] $end
$var wire 1 $ cout $end
$var wire 1 % Zero $end
$var wire 32 & WriteData [31:0] $end
$var wire 32 ' Adr [31:0] $end
$var reg 4 ( ALUControl [3:0] $end
$var reg 2 ) ALUSrcA [1:0] $end
$var reg 2 * ALUSrcB [1:0] $end
$var reg 1 + AdrSrc $end
$var reg 1 , IRWrite $end
$var reg 3 - ImmSrc [2:0] $end
$var reg 1 . PCWrite $end
$var reg 32 / ReadData [31:0] $end
$var reg 1 0 RegWrite $end
$var reg 2 1 ResultSrc [1:0] $end
$var reg 1 2 clk $end
$var reg 1 3 reset $end
$scope module dut $end
$var wire 4 4 ALUControl [3:0] $end
$var wire 2 5 ALUSrcA [1:0] $end
$var wire 2 6 ALUSrcB [1:0] $end
$var wire 1 + AdrSrc $end
$var wire 1 , IRWrite $end
$var wire 3 7 ImmSrc [2:0] $end
$var wire 1 . PCWrite $end
$var wire 32 8 ReadData [31:0] $end
$var wire 1 0 RegWrite $end
$var wire 2 9 ResultSrc [1:0] $end
$var wire 1 2 clk $end
$var wire 1 : memwrite $end
$var wire 1 3 reset $end
$var wire 1 ! sign $end
$var wire 1 " overflow $end
$var wire 32 ; instr [31:0] $end
$var wire 3 < funct3 [2:0] $end
$var wire 1 $ cout $end
$var wire 1 % Zero $end
$var wire 32 = WriteData [31:0] $end
$var wire 32 > SrcB [31:0] $end
$var wire 32 ? SrcA [31:0] $end
$var wire 32 @ Result [31:0] $end
$var wire 32 A RD2 [31:0] $end
$var wire 32 B RD1 [31:0] $end
$var wire 32 C PC [31:0] $end
$var wire 32 D OldPC [31:0] $end
$var wire 32 E ImmExt [31:0] $end
$var wire 32 F Data [31:0] $end
$var wire 32 G Adr [31:0] $end
$var wire 32 H ALUResult [31:0] $end
$var wire 32 I ALUOut [31:0] $end
$var wire 32 J A [31:0] $end
$var reg 32 K aligned_address [31:0] $end
$scope module AReg $end
$var wire 1 2 clk $end
$var wire 1 3 reset $end
$var wire 32 L d [31:0] $end
$var parameter 32 M WIDTH $end
$var reg 32 N q [31:0] $end
$upscope $end
$scope module BReg $end
$var wire 1 2 clk $end
$var wire 1 3 reset $end
$var wire 32 O d [31:0] $end
$var parameter 32 P WIDTH $end
$var reg 32 Q q [31:0] $end
$upscope $end
$scope module adrMux $end
$var wire 32 R b [31:0] $end
$var wire 1 + sel $end
$var wire 32 S out [31:0] $end
$var wire 32 T a [31:0] $end
$var parameter 32 U WIDTH $end
$upscope $end
$scope module alu $end
$var wire 4 V aluc [3:0] $end
$var wire 32 W src2 [31:0] $end
$var wire 32 X src1 [31:0] $end
$var wire 5 Y shamt [4:0] $end
$var reg 1 $ cout $end
$var reg 32 Z out [31:0] $end
$var reg 1 " overflow $end
$var reg 1 ! sign $end
$var reg 33 [ tmp [32:0] $end
$var reg 1 % zero $end
$upscope $end
$scope module aluReg $end
$var wire 1 2 clk $end
$var wire 32 \ d [31:0] $end
$var wire 1 3 reset $end
$var parameter 32 ] WIDTH $end
$var reg 32 ^ q [31:0] $end
$upscope $end
$scope module dataReg $end
$var wire 1 2 clk $end
$var wire 32 _ d [31:0] $end
$var wire 1 3 reset $end
$var parameter 32 ` WIDTH $end
$var reg 32 a q [31:0] $end
$upscope $end
$scope module ext $end
$var wire 3 b ImmSrc [2:0] $end
$var wire 25 c instr [31:7] $end
$var wire 32 d imm_u [31:0] $end
$var wire 32 e imm_s [31:0] $end
$var wire 32 f imm_j [31:0] $end
$var wire 32 g imm_i [31:0] $end
$var wire 32 h imm_b [31:0] $end
$var reg 32 i imm_out [31:0] $end
$upscope $end
$scope module instrReg $end
$var wire 1 2 clk $end
$var wire 32 j d [31:0] $end
$var wire 1 , en $end
$var wire 1 3 reset $end
$var parameter 32 k WIDTH $end
$var reg 32 l q [31:0] $end
$upscope $end
$scope module oldPcReg $end
$var wire 1 2 clk $end
$var wire 1 , en $end
$var wire 1 3 reset $end
$var wire 32 m d [31:0] $end
$var parameter 32 n WIDTH $end
$var reg 32 o q [31:0] $end
$upscope $end
$scope module pcFlop $end
$var wire 1 2 clk $end
$var wire 1 . en $end
$var wire 1 3 reset $end
$var wire 32 p d [31:0] $end
$var parameter 32 q WIDTH $end
$var reg 32 r q [31:0] $end
$upscope $end
$scope module resultMux $end
$var wire 32 s in0 [31:0] $end
$var wire 32 t in1 [31:0] $end
$var wire 32 u in2 [31:0] $end
$var wire 32 v in3 [31:0] $end
$var wire 2 w sel [1:0] $end
$var parameter 32 x WIDTH $end
$var reg 32 y out [31:0] $end
$upscope $end
$scope module rf $end
$var wire 1 2 clk $end
$var wire 5 z rd [4:0] $end
$var wire 32 { rd1 [31:0] $end
$var wire 32 | rd2 [31:0] $end
$var wire 5 } rs1 [4:0] $end
$var wire 5 ~ rs2 [4:0] $end
$var wire 32 !" wd [31:0] $end
$var wire 1 0 we $end
$var reg 32 "" rd1_reg [31:0] $end
$var reg 32 #" rd2_reg [31:0] $end
$upscope $end
$scope module srcAmux $end
$var wire 32 $" in0 [31:0] $end
$var wire 32 %" in1 [31:0] $end
$var wire 32 &" in2 [31:0] $end
$var wire 2 '" sel [1:0] $end
$var parameter 32 (" WIDTH $end
$var reg 32 )" out [31:0] $end
$upscope $end
$scope module srcBmux $end
$var wire 32 *" in0 [31:0] $end
$var wire 32 +" in1 [31:0] $end
$var wire 32 ," in2 [31:0] $end
$var wire 2 -" sel [1:0] $end
$var parameter 32 ." WIDTH $end
$var reg 32 /" out [31:0] $end
$upscope $end
$upscope $end
$upscope $end
$enddefinitions $end
$comment Show the parameter values. $end
$dumpall
b100000 ."
b100000 ("
b100000 x
b100000 q
b100000 n
b100000 k
b100000 `
b100000 ]
b100000 U
b100000 P
b100000 M
$end
#0
$dumpvars
b0 /"
bx -"
b100 ,"
b0 +"
bx *"
b0 )"
bx '"
bx &"
bx %"
bx $"
bx #"
bx ""
bx !"
bx ~
bx }
bx |
bx {
bx z
bx y
bx w
b0 v
b0 u
bx t
bx s
bx r
bx p
bx o
bx m
bx l
bx j
b0 i
bx0 h
bx g
bx0 f
bx e
bx000000000000 d
bx c
bx b
bx a
bx _
bx ^
b0 \
b0 [
b0 Z
b0 Y
b0 X
b0 W
bx V
bx T
bx S
bx R
bx Q
bx O
bx N
bx L
bx K
bx J
bx I
b0 H
bx G
bx F
b0 E
bx D
bx C
bx B
bx A
bx @
b0 ?
b0 >
bx =
bx <
bx ;
0:
bx 9
bx 8
bx 7
bx 6
bx 5
bx 4
03
02
bx 1
x0
bx /
x.
bx -
x,
x+
bx *
bx )
bx (
bx '
bx &
1%
0$
bx #
0"
0!
$end
#5
b0 K
b0 R
b0 I
b0 ^
b0 s
12
#10
13
02
#15
b0 g
b0 e
b0 h
b0 d
b0 f
b0 c
b0 z
b0 ~
b0 }
b0 <
b0 '
b0 G
b0 S
b0 F
b0 a
b0 t
b0 #
b0 ;
b0 l
b0 D
b0 o
b0 %"
b0 &
b0 =
b0 Q
b0 *"
b0 J
b0 N
b0 &"
b0 C
b0 T
b0 m
b0 r
b0 $"
12
#20
1,
b1010111100000000100010111 /
b1010111100000000100010111 8
b1010111100000000100010111 _
b1010111100000000100010111 j
03
02
#25
b10101 g
b10 e
b10 h
b1010111100000000000000000 d
b11100000100000010100 f
bx '
bx G
bx S
b101011110000000010 c
b10 z
b10101 ~
b11100 }
bx C
bx T
bx m
bx r
bx $"
b0 A
b0 O
b0 |
b0 #"
b0 B
b0 L
b0 {
b0 ""
bx J
bx N
bx &"
bx &
bx =
bx Q
bx *"
b1010111100000000100010111 #
b1010111100000000100010111 ;
b1010111100000000100010111 l
b1010111100000000100010111 F
b1010111100000000100010111 a
b1010111100000000100010111 t
12
#30
b10101 Y
x!
x"
x$
bx H
bx Z
bx \
bx [
x%
b10101 >
b10101 W
b10101 /"
bx ?
bx X
bx )"
b10101 E
b10101 i
b10101 u
b10101 +"
b0 @
b0 p
b0 y
b0 !"
b0 (
b0 4
b0 V
b1 *
b1 6
b1 -"
b10 )
b10 5
b10 '"
b0 -
b0 7
b0 b
b0 1
b0 9
b0 w
10
0,
02
#35
0!
0%
0"
0$
b10101 [
b10101 H
b10101 Z
b10101 \
bx @
bx p
bx y
bx !"
bx K
bx R
bx '
bx G
bx S
b0 ?
b0 X
b0 )"
bx D
bx o
bx %"
bx I
bx ^
bx s
b0 &
b0 =
b0 Q
b0 *"
b0 J
b0 N
b0 &"
bx A
bx O
bx |
bx #"
bx B
bx L
bx {
bx ""
b0 C
b0 T
b0 m
b0 r
b0 $"
12
#40
1,
b10100000000000000110011 /
b10100000000000000110011 8
b10100000000000000110011 _
b10100000000000000110011 j
00
02
#45
b101 Y
b101 >
b101 W
b101 /"
b101 E
b101 i
b101 u
b101 +"
x!
x%
x"
x$
bx [
bx H
bx Z
bx \
b101 g
b0 e
b0 h
b10100000000000000000000 d
b100000000100 f
b10101 K
b10101 R
bx ?
bx X
bx )"
b1010000000000000 c
b0 z
b101 ~
b0 }
b10101 @
b10101 p
b10101 y
b10101 !"
bx C
bx T
bx m
bx r
bx $"
bx J
bx N
bx &"
bx &
bx =
bx Q
bx *"
b10101 I
b10101 ^
b10101 s
b0 D
b0 o
b0 %"
b10100000000000000110011 #
b10100000000000000110011 ;
b10100000000000000110011 l
b10100000000000000110011 F
b10100000000000000110011 a
b10100000000000000110011 t
12
#50
bx Y
x!
x%
x"
x$
bx [
bx H
bx Z
bx \
bx >
bx W
bx /"
b0 *
b0 6
b0 -"
0,
02
#55
bx @
bx p
bx y
bx !"
bx K
bx R
bx '
bx G
bx S
bx D
bx o
bx %"
bx I
bx ^
bx s
b0 B
b0 L
b0 {
b0 ""
b10101 C
b10101 T
b10101 m
b10101 r
b10101 $"
12
